{
    "manifest_version": 3,
    "name": "Email Suite - Email Tracker for Gmail",
    "version": "1.0.0",
    "description": "Track email opens, clicks, and boost productivity",
    "permissions": [
        "storage",
        "activeTab",
        "scripting",
        "notifications",
        "alarms"
    ],
    "host_permissions": [
        "https://mail.google.com/*",
        "https://*.emailsuite.com/*"
    ],
    "background": {
        "service_worker": "background.js",
        "type": "module"
    },
    "content_scripts": [
        {
            "matches": ["https://mail.google.com/*"],
            "js": ["content-scripts/gmail-injector.js"]
        }
    ],
    "action": {
        "default_popup": "src/popup/index.html",
        "default_title": "Email Suite"
    },
    "web_accessible_resources": [
        {
            "resources": ["vite.svg"],
            "matches": ["https://mail.google.com/*"]
        }
    ]
}